spectcube/__init__.py
spectcube/resampling.py
spectcube/util.py
spectcube/data/spec-1665-52976-0519.fits
spectcube/example/1_1D_first_example.py
spectcube/example/2_1D_miles_model_with_util.py
spectcube/example/3_1D_resampling_with_uncertainties.py
spectcube/example/4_2D_resampling_multiple_models.py
spectcube/example/5_3D_resampling_datacube.py
spectcube/model/Mun1.30Zm0.40T00.0631_iPp0.00_baseFe_linear_FWHM_2.51.fits
spectcube/model/Mun1.30Zm0.40T00.0794_iPp0.00_baseFe_linear_FWHM_2.51.fits
spectcube/model/Mun1.30Zm0.40T00.1000_iPp0.00_baseFe_linear_FWHM_2.51.fits
spectcube-0.1.0.dist-info/LICENSE.md
spectcube-0.1.0.dist-info/METADATA
spectcube-0.1.0.dist-info/WHEEL
spectcube-0.1.0.dist-info/top_level.txt
spectcube-0.1.0.dist-info/RECORD
