Metadata-Version: 2.1
Name: spectcube
Version: 0.1.0
Summary: Resampling spectrums in 1D, 2D or 3D shapes.
Home-page: https://github.com/luizsl/SpectCube
Author: Luiz Albérico
Author-email: luiz.sl@outlook.com
License: UNKNOWN
Project-URL: Bug Tracker, https://github.com/luizsl/SpectCube/issues
Platform: UNKNOWN
Classifier: Programming Language :: Python :: 3
Classifier: License :: OSI Approved :: BSD License
Classifier: Operating System :: OS Independent
Requires-Python: >=3.7
License-File: LICENSE.md
Requires-Dist: numpy (>=1.17)
Requires-Dist: scipy (>=1.1)
Requires-Dist: astropy
Requires-Dist: matplotlib
